.gitignore
LICENSE
README.rst
brocoli-runner.py
setup.py
brocoli/__init__.py
brocoli/__main__.py
brocoli/brocoli.py
brocoli/catalog.py
brocoli/config.py
brocoli/config_option.py
brocoli/dialog.py
brocoli/exceptions.py
brocoli/form.py
brocoli/irodscatalog.py
brocoli/irodsdom.py
brocoli/listmanager.py
brocoli/navbar.py
brocoli/preferences.py
brocoli/progress_dialog.py
brocoli/treewidget.py
brocoli.egg-info/PKG-INFO
brocoli.egg-info/SOURCES.txt
brocoli.egg-info/dependency_links.txt
brocoli.egg-info/entry_points.txt
brocoli.egg-info/requires.txt
brocoli.egg-info/top_level.txt