Metadata-Version: 2.1
Name: brocoli
Version: 0.7.3
Summary: Browse Collections for iRODS
Home-page: https://github.com/mesocentre-mcia/brocoli
Author: Pierre Gay
Author-email: pierre.gay@u-bordeaux.fr
License: UNKNOWN
Keywords: irods,tkinter
Platform: UNKNOWN
Classifier: License :: OSI Approved :: BSD License
Classifier: Development Status :: 3 - Alpha
Classifier: Programming Language :: Python :: 2.7
Classifier: Programming Language :: Python :: 3.5
Classifier: Programming Language :: Python :: 3.6
Classifier: Operating System :: POSIX :: Linux
Classifier: Topic :: Desktop Environment :: File Managers
Requires-Python: >=2.7
License-File: LICENSE
